{
  "title": "FluencyDrop 4",
  "language": "pl-PL",
  "notes": "Nieoczekiwane opóźnienie w górach",
  "tags": [
     "FluencyDrop", "B1"
  ],


  "data": [
    {
      "text": "Rano Marek był bardzo podekscytowany swoją wycieczką w góry."
    },
    {
      "text": "Marzył o widokach i świeżym powietrzu."
    },
    {
      "text": "Wysiadł na małej stacji i zaczął iść szlakiem."
    },
    {
      "text": "Jednak po pewnym czasie zauważył, że droga jest zamknięta."
    },
    {
      "text": "Mężczyzna nie wiedział dlaczego."
    },
    {
      "text": "Postanowił wrócić do stacji i zapytać innych podróżnych."
    },
    {
      "text": "Dowiedział się, że spadł duży deszcz i teren jest niebezpieczny."
    },
    {
      "text": "Marek poczuł się zawiedziony, bo całą drogę zaplanował inaczej."
    },
    {
      "text": "Zamiast iść na szczyt, poszedł do małego schroniska blisko stacji."
    },
    {
      "text": "Tam spotkał kilku turystów, którzy mieli podobne plany."
    },
    {
      "text": "Razem postanowili zostawić górskie wędrówki na inny dzień i spędzić czas grając w karty i rozmawiając."
    },
    {
      "text": "Marek zrozumiał, że czasem plany mogą się zmienić, a niespodziewane sytuacje też mogą przynieść miłe chwile."
    },
    {
      "text": "Wieczorem, gdy deszcz ustał, wyszedł na krótki spacer."
    },
    {
      "text": "Pokój i spokój gór był zupełnie inny niż ten, o którym marzył, ale też wyjątkowy."
    },
    {
      "text": "Nie zawsze podróż musi być pełna przygód."
    },
    {
      "text": "Czasem to chwile spokoju i prostych radości tworzą najlepsze wspomnienia."
    }
  ]



}